kyouka/__init__.py
kyouka/cli.py
kyouka/main.py
kyouka_cli-1.0.0.dist-info/licenses/LICENSE
kyouka_cli-1.0.0.dist-info/METADATA
kyouka_cli-1.0.0.dist-info/WHEEL
kyouka_cli-1.0.0.dist-info/entry_points.txt
kyouka_cli-1.0.0.dist-info/top_level.txt
kyouka_cli-1.0.0.dist-info/RECORD
