Metadata-Version: 2.4
Name: kyouka-cli
Version: 1.0.0
Summary: yt tl ripoff for ur terminal
Home-page: https://github.com/lyraxial/kyouka
Author: vyx
Author-email: kiyoshi.dev31@gmail.com
License: MIT
Project-URL: Homepage, https://github.com/lyraxial/kyouka
Project-URL: Repository, https://github.com/lyraxial/kyouka
Project-URL: Issues, https://github.com/lyraxial/kyouka/issues
Keywords: youtube,downloader,media,player,cli
Classifier: Development Status :: 4 - Beta
Classifier: Environment :: Console
Classifier: Intended Audience :: End Users/Desktop
Classifier: Programming Language :: Python :: 3
Classifier: Programming Language :: Python :: 3.7
Classifier: Programming Language :: Python :: 3.8
Classifier: Programming Language :: Python :: 3.9
Classifier: Programming Language :: Python :: 3.10
Classifier: Programming Language :: Python :: 3.11
Classifier: License :: OSI Approved :: MIT License
Classifier: Operating System :: OS Independent
Classifier: Topic :: Multimedia :: Video
Classifier: Topic :: Internet :: WWW/HTTP
Requires-Python: >=3.6
License-File: LICENSE
Requires-Dist: yt-dlp>=2023.1.6
Requires-Dist: pygame>=2.0.0
Requires-Dist: pillow>=8.0.0
Provides-Extra: full
Requires-Dist: opencv-python>=4.5.0; extra == "full"
Requires-Dist: python-vlc>=3.0.0; extra == "full"
Dynamic: author-email
Dynamic: home-page
Dynamic: license-file
Dynamic: requires-python
